dash_tabler_icons/DashTablerIcons.py
dash_tabler_icons/__init__.py
dash_tabler_icons/_imports_.py
dash_tabler_icons/dash_tabler_icons.min.js
dash_tabler_icons/dash_tabler_icons.min.js.map
dash_tabler_icons/icons.py
dash_tabler_icons/metadata.json
dash_tabler_icons/package-info.json
dash_tabler_icons-0.0.1.dist-info/LICENSE
dash_tabler_icons-0.0.1.dist-info/METADATA
dash_tabler_icons-0.0.1.dist-info/WHEEL
dash_tabler_icons-0.0.1.dist-info/top_level.txt
dash_tabler_icons-0.0.1.dist-info/RECORD
