Metadata-Version: 2.1
Name: dash_tabler_icons
Version: 0.0.1
Summary: tabler-icons for Dash
Author: Ploomber Inc. <contact@ploomber.io>
License: Apache-2.0
Classifier: Framework :: Dash
License-File: LICENSE
